mypackage_at21/__init__.py
mypackage_at21/mymodule.py
mypackage_at21-0.1.1.dist-info/METADATA
mypackage_at21-0.1.1.dist-info/WHEEL
mypackage_at21-0.1.1.dist-info/top_level.txt
mypackage_at21-0.1.1.dist-info/RECORD
