Metadata-Version: 2.2
Name: mypackage_at21
Version: 0.1.1
Summary: A Python package with a submodule
Home-page: https://github.ibm.com/ANNIE-THOMAS1/sample_building_blocks
Author: Annie Thomas
Author-email: Annie Thomas <annie.thomas1@ibm.com>
Requires-Python: >=3.6
Dynamic: author
Dynamic: home-page
Dynamic: requires-python
